pytest_requirements/__init__.py
pytest_requirements/_version.py
pytest_requirements/test_plugin.py
pytest_requirements-0.2.0.dist-info/LICENSE
pytest_requirements-0.2.0.dist-info/METADATA
pytest_requirements-0.2.0.dist-info/WHEEL
pytest_requirements-0.2.0.dist-info/entry_points.txt
pytest_requirements-0.2.0.dist-info/top_level.txt
pytest_requirements-0.2.0.dist-info/RECORD
